Python_dictionaries_deep_merge/Python_dictionaries_deep_merge.py
Python_dictionaries_deep_merge/__init__.py
Python_dictionaries_deep_merge-1.1.dist-info/METADATA
Python_dictionaries_deep_merge-1.1.dist-info/WHEEL
Python_dictionaries_deep_merge-1.1.dist-info/top_level.txt
Python_dictionaries_deep_merge-1.1.dist-info/RECORD
