Metadata-Version: 2.1
Name: Python-dictionaries-deep-merge
Version: 1.1
Home-page: https://github.com/hbcha0916/Python_dictionaries_deep_merge.git
Author: hbcha
Author-email: hbcha0916@naver.com
License: hbcha0916
